{"remove":{"path":"part-00001-4508d6dc-3929-429a-bcbe-ef2f3c9d5dbe-c000.snappy.parquet","dataChange":true,"deletionTimestamp":1758887685471,"extendedFileMetadata":true,"partitionValues":{},"size":73934}}
{"add":{"path":"part-00001-3a801c14-2938-4a6a-97db-c17ddd9a79e1-c000.snappy.parquet","partitionValues":{},"size":73929,"modificationTime":1758887685513,"dataChange":true,"stats":"{\"numRecords\":1418,\"minValues\":{\"Volume\":2168200,\"Close\":36.70741271972656,\"Low\":36.624405865223764,\"ticker\":\"ORCL\",\"Date\":\"2020-01-02T00:00:00Z\",\"Open\":37.92484424024546,\"High\":40.027683381555235},\"maxValues\":{\"Date\":\"2025-08-22T00:00:00Z\",\"ticker\":\"ORCL\",\"Volume\":68605700,\"High\":260.8699951171875,\"Low\":253.32000732421875,\"Close\":256.42999267578125,\"Open\":257.7099914550781},\"nullCount\":{\"Date\":0,\"Close\":0,\"High\":0,\"Low\":0,\"Open\":0,\"Volume\":0,\"ticker\":0}}","tags":null,"baseRowId":null,"defaultRowCommitVersion":null,"clusteringProvider":null}}
{"commitInfo":{"timestamp":1758887685514,"operation":"WRITE","operationParameters":{"mode":"Overwrite"},"engineInfo":"delta-rs:py-1.1.1","clientVersion":"delta-rs.py-1.1.1","operationMetrics":{"execution_time_ms":71,"num_added_files":1,"num_added_rows":1418,"num_partitions":0,"num_removed_files":1}}}